sort_css_declarations/__init__.py
sort_css_declarations/sort_css_declarations.py
sort_css_declarations-1.0.2.dist-info/LICENSE
sort_css_declarations-1.0.2.dist-info/METADATA
sort_css_declarations-1.0.2.dist-info/WHEEL
sort_css_declarations-1.0.2.dist-info/entry_points.txt
sort_css_declarations-1.0.2.dist-info/top_level.txt
sort_css_declarations-1.0.2.dist-info/RECORD
