Metadata-Version: 2.1
Name: sort-css-declarations
Version: 1.0.2
Summary: Tool for sorting CSS file declarations.
Home-page: https://github.com/heloint/sort_css_declarations
Author: Dániel Májer
Author-email: majerdaniel93@gmail.com
License: MIT
Project-URL: Homepage, https://github.com/heloint/sort_css_declarations
Project-URL: Bug Tracker, https://github.com/heloint/sort_css_declarations/issues
Classifier: License :: OSI Approved :: MIT License
Classifier: Programming Language :: Python :: 3
Classifier: Programming Language :: Python :: 3 :: Only
Classifier: Programming Language :: Python :: Implementation :: CPython
Classifier: Operating System :: OS Independent
Requires-Python: >=3.7
License-File: LICENSE
Requires-Dist: beautifulsoup4 (>=4.11.1)
Requires-Dist: bs4 (>=0.0.1)
Requires-Dist: cssutils (>=2.6.0)
Requires-Dist: soupsieve (>=2.3.2)
